blueguard_client/__about__.py
blueguard_client/__init__.py
blueguard_client/blueguard_client.py
blueguard_client/client_example.py
blueguard_client/load_test_example.py
blueguard_client/components/__init__.py
blueguard_client/components/blueguard_requests.py
blueguard_client/components/blueguard_response.py
blueguard_client/components/blueguard_uris.py
blueguard_client/components/modes.py
blueguard_client/components/request_objects.py
blueguard_client/tests/test_client.py
blueguard_client-0.0.dev3.dist-info/METADATA
blueguard_client-0.0.dev3.dist-info/WHEEL
blueguard_client-0.0.dev3.dist-info/licenses/LICENSE
blueguard_client-0.0.dev3.dist-info/RECORD
