Metadata-Version: 2.3
Name: blueguard_client
Version: 0.0.dev3
Summary: A thin client for interacting with the Blueguard Privacy AI for de-identication and re-identication API.
Project-URL: Homepage, https://github.com/bluegennx-ai/blueguard-thin-client/
Project-URL: Bug Tracker, https://github.com/bluegennx-ai/blueguard-thin-client/issues/
Project-URL: Changelog, https://github.com/bluegennx-ai/blueguard-thin-client/blob/main/CHANGELOG.md
Author-email: Chakravarthy Varaga <chakravarthy.varaga@bluegennx.ai>
License-File: LICENSE
Classifier: License :: OSI Approved :: MIT License
Classifier: Operating System :: OS Independent
Classifier: Programming Language :: Python :: 3
Requires-Python: >=3.8
Requires-Dist: python-dotenv==1.0.1
Requires-Dist: requests~=2.31.0
